odoo/addons/test_extendable_pydantic_fastapi/README.rst
odoo/addons/test_extendable_pydantic_fastapi/__init__.py
odoo/addons/test_extendable_pydantic_fastapi/__manifest__.py
odoo/addons/test_extendable_pydantic_fastapi/routers.py
odoo/addons/test_extendable_pydantic_fastapi/schemas.py
odoo/addons/test_extendable_pydantic_fastapi/i18n/test_extendable_pydantic_fastapi.pot
odoo/addons/test_extendable_pydantic_fastapi/models/__init__.py
odoo/addons/test_extendable_pydantic_fastapi/models/fastapi_endpoint.py
odoo/addons/test_extendable_pydantic_fastapi/readme/CONTRIBUTORS.rst
odoo/addons/test_extendable_pydantic_fastapi/readme/DESCRIPTION.rst
odoo/addons/test_extendable_pydantic_fastapi/static/description/icon.png
odoo/addons/test_extendable_pydantic_fastapi/static/description/index.html
odoo/addons/test_extendable_pydantic_fastapi/tests/__init__.py
odoo/addons/test_extendable_pydantic_fastapi/tests/test_user.py
odoo_addon_test_extendable_pydantic_fastapi-16.0.2.0.1.dist-info/METADATA
odoo_addon_test_extendable_pydantic_fastapi-16.0.2.0.1.dist-info/WHEEL
odoo_addon_test_extendable_pydantic_fastapi-16.0.2.0.1.dist-info/top_level.txt
odoo_addon_test_extendable_pydantic_fastapi-16.0.2.0.1.dist-info/RECORD
